Workbook

Sheet Synthèse
B2: CAHIER DE RECETTE — AITE HOUSE
B3: Suite de gestion hôtelière sur Odoo 18 — 12 modules
B4: AITE Consulting SARL · info@aite-consulting.com · (+237) 673 373 367
B6: IDENTIFICATION DE LA RECETTE
B7: Client / établissement
B8: Version testée | C8: AITE HOUSE — septembre 2026
B9: Environnement | C9: Recette
B10: Base de données
B11: Date de début
B12: Date de fin
B13: Testeur principal
B14: Responsable AITE
B16: Cellules sur fond jaune : à compléter. Saisir les résultats dans l'onglet « Cas de test ».
B18: AVANCEMENT GLOBAL | G18: AVANCEMENT PAR DOMAINE
B19: Statut | C19: Nombre | D19: Part | G19: Domaine | H19: Module | I19: Cas | J19: OK | K19: KO | L19: Reste à tester
B20: À tester | C20: =COUNTIF('Cas de test'!$I$2:$I$200,$B20) | D20: =IFERROR($C20/$C$25,0) | G20: Hébergement — chambres & séjours | H20: aite_hotel_management | I20: =COUNTIF('Cas de test'!$B$2:$B$200,$G20) | J20: =COUNTIFS('Cas de test'!$B$2:$B$200,$G20,'Cas de test'!$I$2:$I$200,"OK") | K20: =COUNTIFS('Cas de test'!$B$2:$B$200,$G20,'Cas de test'!$I$2:$I$200,"KO") | L20: =COUNTIFS('Cas de test'!$B$2:$B$200,$G20,'Cas de test'!$I$2:$I$200,"À tester")
B21: OK | C21: =COUNTIF('Cas de test'!$I$2:$I$200,$B21) | D21: =IFERROR($C21/$C$25,0) | G21: Espaces & prestations | H21: aite_slot_booking | I21: =COUNTIF('Cas de test'!$B$2:$B$200,$G21) | J21: =COUNTIFS('Cas de test'!$B$2:$B$200,$G21,'Cas de test'!$I$2:$I$200,"OK") | K21: =COUNTIFS('Cas de test'!$B$2:$B$200,$G21,'Cas de test'!$I$2:$I$200,"KO") | L21: =COUNTIFS('Cas de test'!$B$2:$B$200,$G21,'Cas de test'!$I$2:$I$200,"À tester")
B22: KO | C22: =COUNTIF('Cas de test'!$I$2:$I$200,$B22) | D22: =IFERROR($C22/$C$25,0) | G22: Réservation en ligne | H22: aite_website_booking | I22: =COUNTIF('Cas de test'!$B$2:$B$200,$G22) | J22: =COUNTIFS('Cas de test'!$B$2:$B$200,$G22,'Cas de test'!$I$2:$I$200,"OK") | K22: =COUNTIFS('Cas de test'!$B$2:$B$200,$G22,'Cas de test'!$I$2:$I$200,"KO") | L22: =COUNTIFS('Cas de test'!$B$2:$B$200,$G22,'Cas de test'!$I$2:$I$200,"À tester")
B23: Bloqué | C23: =COUNTIF('Cas de test'!$I$2:$I$200,$B23) | D23: =IFERROR($C23/$C$25,0) | G23: Point de vente & caisse | H23: aite_pos_analytics | I23: =COUNTIF('Cas de test'!$B$2:$B$200,$G23) | J23: =COUNTIFS('Cas de test'!$B$2:$B$200,$G23,'Cas de test'!$I$2:$I$200,"OK") | K23: =COUNTIFS('Cas de test'!$B$2:$B$200,$G23,'Cas de test'!$I$2:$I$200,"KO") | L23: =COUNTIFS('Cas de test'!$B$2:$B$200,$G23,'Cas de test'!$I$2:$I$200,"À tester")
B24: Non applicable | C24: =COUNTIF('Cas de test'!$I$2:$I$200,$B24) | D24: =IFERROR($C24/$C$25,0) | G24: Note de chambre | H24: aite_hotel_pos_link | I24: =COUNTIF('Cas de test'!$B$2:$B$200,$G24) | J24: =COUNTIFS('Cas de test'!$B$2:$B$200,$G24,'Cas de test'!$I$2:$I$200,"OK") | K24: =COUNTIFS('Cas de test'!$B$2:$B$200,$G24,'Cas de test'!$I$2:$I$200,"KO") | L24: =COUNTIFS('Cas de test'!$B$2:$B$200,$G24,'Cas de test'!$I$2:$I$200,"À tester")
B25: TOTAL | C25: =COUNTA('Cas de test'!$A$2:$A$200) | D25: =IFERROR(SUM($D$20:$D$24),0) | G25: Crédit clients (ardoises) | H25: aite_pos_credit | I25: =COUNTIF('Cas de test'!$B$2:$B$200,$G25) | J25: =COUNTIFS('Cas de test'!$B$2:$B$200,$G25,'Cas de test'!$I$2:$I$200,"OK") | K25: =COUNTIFS('Cas de test'!$B$2:$B$200,$G25,'Cas de test'!$I$2:$I$200,"KO") | L25: =COUNTIFS('Cas de test'!$B$2:$B$200,$G25,'Cas de test'!$I$2:$I$200,"À tester")
G26: Fidélité | H26: aite_loyalty | I26: =COUNTIF('Cas de test'!$B$2:$B$200,$G26) | J26: =COUNTIFS('Cas de test'!$B$2:$B$200,$G26,'Cas de test'!$I$2:$I$200,"OK") | K26: =COUNTIFS('Cas de test'!$B$2:$B$200,$G26,'Cas de test'!$I$2:$I$200,"KO") | L26: =COUNTIFS('Cas de test'!$B$2:$B$200,$G26,'Cas de test'!$I$2:$I$200,"À tester")
B27: Taux de réussite (OK / testés) | C27: =IFERROR($C$21/($C$21+$C$22),0) | G27: Stock & inventaire | H27: aite_stock_dashboard | I27: =COUNTIF('Cas de test'!$B$2:$B$200,$G27) | J27: =COUNTIFS('Cas de test'!$B$2:$B$200,$G27,'Cas de test'!$I$2:$I$200,"OK") | K27: =COUNTIFS('Cas de test'!$B$2:$B$200,$G27,'Cas de test'!$I$2:$I$200,"KO") | L27: =COUNTIFS('Cas de test'!$B$2:$B$200,$G27,'Cas de test'!$I$2:$I$200,"À tester")
B28: Cas critiques en échec (bloquants) | C28: =COUNTIFS('Cas de test'!$D$2:$D$200,"1 - Critique",'Cas de test'!$I$2:$I$200,"KO") | G28: Achats & fournisseurs | H28: aite_purchase_dashboard | I28: =COUNTIF('Cas de test'!$B$2:$B$200,$G28) | J28: =COUNTIFS('Cas de test'!$B$2:$B$200,$G28,'Cas de test'!$I$2:$I$200,"OK") | K28: =COUNTIFS('Cas de test'!$B$2:$B$200,$G28,'Cas de test'!$I$2:$I$200,"KO") | L28: =COUNTIFS('Cas de test'!$B$2:$B$200,$G28,'Cas de test'!$I$2:$I$200,"À tester")
G29: Pilotage — vue Direction | H29: aite_direction_dashboard | I29: =COUNTIF('Cas de test'!$B$2:$B$200,$G29) | J29: =COUNTIFS('Cas de test'!$B$2:$B$200,$G29,'Cas de test'!$I$2:$I$200,"OK") | K29: =COUNTIFS('Cas de test'!$B$2:$B$200,$G29,'Cas de test'!$I$2:$I$200,"KO") | L29: =COUNTIFS('Cas de test'!$B$2:$B$200,$G29,'Cas de test'!$I$2:$I$200,"À tester")
G30: Tableau de bord exécutif | H30: aite_exec_dashboard | I30: =COUNTIF('Cas de test'!$B$2:$B$200,$G30) | J30: =COUNTIFS('Cas de test'!$B$2:$B$200,$G30,'Cas de test'!$I$2:$I$200,"OK") | K30: =COUNTIFS('Cas de test'!$B$2:$B$200,$G30,'Cas de test'!$I$2:$I$200,"KO") | L30: =COUNTIFS('Cas de test'!$B$2:$B$200,$G30,'Cas de test'!$I$2:$I$200,"À tester")
G31: Jeu de démonstration | H31: aite_demo_data | I31: =COUNTIF('Cas de test'!$B$2:$B$200,$G31) | J31: =COUNTIFS('Cas de test'!$B$2:$B$200,$G31,'Cas de test'!$I$2:$I$200,"OK") | K31: =COUNTIFS('Cas de test'!$B$2:$B$200,$G31,'Cas de test'!$I$2:$I$200,"KO") | L31: =COUNTIFS('Cas de test'!$B$2:$B$200,$G31,'Cas de test'!$I$2:$I$200,"À tester")
G32: Transverse — sécurité, données, exploitation | H32: tous modules | I32: =COUNTIF('Cas de test'!$B$2:$B$200,$G32) | J32: =COUNTIFS('Cas de test'!$B$2:$B$200,$G32,'Cas de test'!$I$2:$I$200,"OK") | K32: =COUNTIFS('Cas de test'!$B$2:$B$200,$G32,'Cas de test'!$I$2:$I$200,"KO") | L32: =COUNTIFS('Cas de test'!$B$2:$B$200,$G32,'Cas de test'!$I$2:$I$200,"À tester")
G33: Taxe de séjour | H33: aite_city_tax | I33: =COUNTIF('Cas de test'!$B$2:$B$200,$G33) | J33: =COUNTIFS('Cas de test'!$B$2:$B$200,$G33,'Cas de test'!$I$2:$I$200,"OK") | K33: =COUNTIFS('Cas de test'!$B$2:$B$200,$G33,'Cas de test'!$I$2:$I$200,"KO") | L33: =COUNTIFS('Cas de test'!$B$2:$B$200,$G33,'Cas de test'!$I$2:$I$200,"À tester")
G34: Registre des clients & statistiques | H34: aite_guest_registry | I34: =COUNTIF('Cas de test'!$B$2:$B$200,$G34) | J34: =COUNTIFS('Cas de test'!$B$2:$B$200,$G34,'Cas de test'!$I$2:$I$200,"OK") | K34: =COUNTIFS('Cas de test'!$B$2:$B$200,$G34,'Cas de test'!$I$2:$I$200,"KO") | L34: =COUNTIFS('Cas de test'!$B$2:$B$200,$G34,'Cas de test'!$I$2:$I$200,"À tester")
G35: Gouvernante, inspections & maintenance | H35: aite_housekeeping | I35: =COUNTIF('Cas de test'!$B$2:$B$200,$G35) | J35: =COUNTIFS('Cas de test'!$B$2:$B$200,$G35,'Cas de test'!$I$2:$I$200,"OK") | K35: =COUNTIFS('Cas de test'!$B$2:$B$200,$G35,'Cas de test'!$I$2:$I$200,"KO") | L35: =COUNTIFS('Cas de test'!$B$2:$B$200,$G35,'Cas de test'!$I$2:$I$200,"À tester")
G36: Indicateurs hôteliers — RevPAR, pickup, pace | H36: aite_exec_dashboard, aite_direction_dashboard | I36: =COUNTIF('Cas de test'!$B$2:$B$200,$G36) | J36: =COUNTIFS('Cas de test'!$B$2:$B$200,$G36,'Cas de test'!$I$2:$I$200,"OK") | K36: =COUNTIFS('Cas de test'!$B$2:$B$200,$G36,'Cas de test'!$I$2:$I$200,"KO") | L36: =COUNTIFS('Cas de test'!$B$2:$B$200,$G36,'Cas de test'!$I$2:$I$200,"À tester")

Sheet Cas de test
A1: ID | B1: Domaine | C1: Module | D1: Priorité | E1: Pré-requis | F1: Scénario | G1: Étapes | H1: Résultat attendu | I1: Statut | J1: Testé par | K1: Date | L1: Anomalie / commentaire
A2: A01 | B2: Hébergement — chambres & séjours | C2: aite_hotel_management | D2: 1 - Critique | E2: Base installée, 1 type de chambre créé | F2: Créer une chambre et la rendre réservable | G2: 1. Hôtel → Configuration → Chambres → Créer. 2. Renseigner numéro, type, capacité, tarif de base en FCFA. 3. Enregistrer, puis ouvrir le planning. | H2: La chambre est enregistrée sans erreur et apparaît dans le planning, en statut Libre sur toute la période. | I2: À tester
A3: A02 | B3: Hébergement — chambres & séjours | C3: aite_hotel_management | D3: 1 - Critique | E3: Au moins 2 chambres disponibles | F3: Créer une réservation directe (walk-in) | G3: 1. Hôtel → Réservations → Créer. 2. Sélectionner client, chambre, dates d'arrivée et de départ. 3. Confirmer la réservation. | H3: La réservation passe en statut Confirmée, le nombre de nuits et le montant total sont calculés automatiquement en FCFA. | I3: À tester
A4: A03 | B4: Hébergement — chambres & séjours | C4: aite_hotel_management | D4: 1 - Critique | E4: Une réservation confirmée existe sur la période | F4: Empêcher la double réservation d'une même chambre | G4: 1. Créer une seconde réservation sur la même chambre avec des dates qui se chevauchent. 2. Tenter de confirmer. | H4: Le système refuse la confirmation ou signale explicitement le conflit ; la chambre n'est pas réservée deux fois. | I4: À tester
A5: A04 | B5: Hébergement — chambres & séjours | C5: aite_hotel_management | D5: 1 - Critique | E5: Réservation confirmée du jour | F5: Effectuer un check-in | G5: 1. Ouvrir la réservation du jour. 2. Cliquer sur Check-in. | H5: Le statut passe à Arrivée / En cours, la chambre devient Occupée dans le planning, et le folio du séjour est créé. | I5: À tester
A6: A05 | B6: Hébergement — chambres & séjours | C6: aite_hotel_management | D6: 1 - Critique | E6: Séjour en cours avec folio ouvert | F6: Ajouter un extra au folio (petit-déjeuner) | G6: 1. Ouvrir le folio du séjour. 2. Ajouter la ligne « Petit-déjeuner » × 2. 3. Enregistrer. | H6: La ligne s'ajoute avec sa date et son montant ; le total du folio est recalculé immédiatement. | I6: À tester
A7: A06 | B7: Hébergement — chambres & séjours | C7: aite_hotel_management | D7: 1 - Critique | E7: Séjour en cours, folio alimenté | F7: Effectuer un check-out et facturer le séjour | G7: 1. Ouvrir la réservation. 2. Cliquer sur Check-out. 3. Générer la facture. | H7: Une facture unique reprend nuitées et extras, la chambre redevient Libre, et le séjour passe en statut Terminé. | I7: À tester
A8: A07 | B8: Hébergement — chambres & séjours | C8: aite_hotel_management | D8: 2 - Majeur | E8: Réservation confirmée, acompte prévu | F8: Enregistrer un acompte et le déduire à la facturation | G8: 1. Saisir un acompte de 20 000 F sur la réservation. 2. Aller jusqu'au check-out et générer la facture. | H8: L'acompte apparaît sur le folio et est déduit du net à payer ; le solde restant dû est exact. | I8: À tester
A9: A08 | B9: Hébergement — chambres & séjours | C9: aite_hotel_management | D9: 2 - Majeur | E9: Réservation confirmée | F9: Éditer une proforma avant le départ | G9: 1. Ouvrir le séjour en cours. 2. Demander l'impression de la proforma. | H9: La proforma s'édite en PDF avec l'en-tête de l'établissement, les lignes du folio et les montants en FCFA. | I9: À tester
A10: A09 | B10: Hébergement — chambres & séjours | C10: aite_hotel_management | D10: 2 - Majeur | E10: Plusieurs chambres, dont une en maintenance | F10: Déclarer une chambre hors service | G10: 1. Passer une chambre en statut Hors service / Maintenance sur une période. 2. Consulter le planning. | H10: La chambre apparaît en Hors service sur la période et n'est plus proposée à la réservation. | I10: À tester
A11: A10 | B11: Hébergement — chambres & séjours | C11: aite_hotel_management | D11: 2 - Majeur | E11: Journée avec arrivées, départs et présents | F11: Consulter la main courante du jour | G11: 1. Ouvrir la main courante / photo du jour. | H11: Les compteurs Présents, Arrivées, Départs et Hors service correspondent exactement à la réalité du planning. | I11: À tester
A12: A11 | B12: Hébergement — chambres & séjours | C12: aite_hotel_management | D12: 2 - Majeur | E12: Réservation confirmée non arrivée | F12: Annuler une réservation et gérer un client non présenté | G12: 1. Annuler une réservation confirmée. 2. Marquer une autre « Non présenté » (bouton de la réservation). | H12: Les statuts sont mis à jour, les chambres se libèrent, et le motif reste consultable dans l'historique. | I12: À tester
A13: A12 | B13: Hébergement — chambres & séjours | C13: aite_hotel_management | D13: 2 - Majeur | E13: Deux types de chambre avec tarifs différents | F13: Appliquer un tarif par type de chambre et par période | G13: 1. Créer une réservation sur chaque type de chambre. 2. Comparer les montants calculés. | H13: Chaque réservation applique le tarif du type de chambre concerné ; les éventuelles listes de prix saisonnières sont respectées. | I13: À tester
... A147: Q07 | B147: Indicateurs hôteliers — RevPAR, pickup, pace | C147: aite_exec_dashboard, aite_direction_dashboard | D147: 1 - Critique | E147: Base neuve, administrateur sans réglage de droits | F147: Ouvrir le cockpit Direction au premier clic | G147: 1. Se connecter en administrateur. 2. Ouvrir Direction → Vue d'ensemble, puis chaque onglet. | H147: Aucune erreur d'accès : l'administrateur reçoit d'office les profils Manager (Analyses POS) et Responsable (Crédit clients). | I147: À tester

Sheet Anomalies
A1: N° | B1: Cas lié | C1: Module | D1: Description | E1: Gravité | F1: Détecté le | G1: Détecté par | H1: Statut | I1: Corrigé le | J1: Vérifié par
A2: 1 | B2: E03 | C2: aite_hotel_pos_link | D2: Exemple : une chambre libre apparaît dans la liste des notes de chambre. | E2: Bloquante | F2: 12/09/2026 | G2: Nom du testeur | H2: Ouverte
A3: ↑ ligne d'exemple à remplacer — saisir les anomalies à partir de la ligne 3

Sheet Mode d'emploi
B2: COMMENT UTILISER CE CAHIER DE RECETTE
B4: 1. Préparer l'environnement
B5: Installer la suite AITE HOUSE sur une base de recette (jamais sur la production). Installer aite_demo_data pour disposer de données, ou partir des données réelles du client selon le contexte.
B7: 2. Dérouler les cas dans l'ordre des domaines
B8: Les cas A à M suivent le parcours naturel de l'établissement : hébergement, espaces, réservation en ligne, caisse, note de chambre, crédit, fidélité, stock, achats, pilotage, puis transverse.
B9: Traiter en priorité les cas « 1 - Critique » : ils conditionnent la mise en production.
B11: 3. Saisir le résultat de chaque cas
B12: Colonne Statut (liste déroulante) : À tester / OK / KO / Bloqué / Non applicable.
B13: Renseigner le testeur, la date, et en cas d'échec une description précise dans la colonne Anomalie.
B15: 4. Journaliser les anomalies
B16: Chaque KO donne lieu à une ligne dans l'onglet Anomalies, avec sa gravité et son statut de correction. La ligne 2 est un exemple à remplacer.
B18: 5. Suivre l'avancement
... B26: Éditeur : AITE Consulting SARL — Douala, Makepe Bloc F — info@aite-consulting.com
